maim_message/__init__.py
maim_message/api.py
maim_message/api_message_base.py
maim_message/client_base.py
maim_message/client_base.py.bak
maim_message/client_factory.py
maim_message/client_ws_api.py
maim_message/client_ws_connection.py
maim_message/connection_interface.py
maim_message/converter.py
maim_message/crypto.py
maim_message/log_queue.py
maim_message/log_utils.py
maim_message/message_base.py
maim_message/message_cache.py
maim_message/multi_client.py
maim_message/router.py
maim_message/server_ws_api.py
maim_message/server_ws_connection.py
maim_message/tcp_connection.py
maim_message/ws_config.py
maim_message/ws_connection.py
maim_message/client/__init__.py
maim_message/message/__init__.py
maim_message/server/__init__.py
maim_message/websocket/__init__.py
maim_message-0.6.8.dist-info/licenses/LICENSE
maim_message-0.6.8.dist-info/METADATA
maim_message-0.6.8.dist-info/WHEEL
maim_message-0.6.8.dist-info/top_level.txt
maim_message-0.6.8.dist-info/RECORD
