Metadata-Version: 2.4
Name: maim_message
Version: 0.6.8
Summary: A message handling library
Home-page: https://github.com/MaiM-with-u/maim_message
Author: tcmofashi
Author-email: mofashiforzbx@qq.com
Requires-Python: >=3.9
License-File: LICENSE
Requires-Dist: fastapi>=0.70.0
Requires-Dist: uvicorn>=0.15.0
Requires-Dist: aiohttp>=3.8.0
Requires-Dist: pydantic>=1.9.0
Requires-Dist: websockets>=10.0
Requires-Dist: cryptography
Dynamic: author-email
Dynamic: description-content-type
Dynamic: home-page
Dynamic: license-file
Dynamic: requires-python
